mircat_v2/__init__.py
mircat_v2/dbase.py
mircat_v2/main.py
mircat_v2/nifti.py
mircat_v2/parallel.py
mircat_v2/configs/__init__.py
mircat_v2/configs/config.py
mircat_v2/configs/dbase_duckdb.sql
mircat_v2/configs/radiomics_params.yaml
mircat_v2/dicom_conversion/__init__.py
mircat_v2/dicom_conversion/converter.py
mircat_v2/radiomics/__init__.py
mircat_v2/radiomics/extractor.py
mircat_v2/segmentation/__init__.py
mircat_v2/segmentation/segmentor.py
mircat_v2/segmentation/models/__init__.py
mircat_v2/stats/__init__.py
mircat_v2/stats/analyzer.py
mircat_v2/stats/aorta.py
mircat_v2/stats/centerline.py
mircat_v2/stats/contrast.py
mircat_v2/stats/contrast_phase_classifiers_2024_07_19.pkl
mircat_v2/stats/iliac.py
mircat_v2/stats/tissues.py
mircat_v2/stats/utilities.py
mircat_v2/stats/vertebrae.py
mircat_v2/stats/vessel.py
mircat_v2/stats/vol_int.py
mircat_v2-1.0.8.dist-info/METADATA
mircat_v2-1.0.8.dist-info/WHEEL
mircat_v2-1.0.8.dist-info/entry_points.txt
mircat_v2-1.0.8.dist-info/licenses/LICENSE
mircat_v2-1.0.8.dist-info/RECORD
